{
  "assetCategories": {
    "decal": {
      "leakage": {
        "stamp": {}
      }
    }
  },
  "averageColor": "#3E3834",
  "categories": [
    "atlas",
    "decals",
    "leakage"
  ],
  "comp_version": 1,
  "description": "",
  "environment": {
    "biome": "undefined",
    "region": "undefined"
  },
  "highest_available_res": 8192,
  "id": "skkvdgfc",
  "json": {
    "contentLength": 6930,
    "uri": "skkvdgfc.json"
  },
  "maps": [
    {
      "averageColor": "#3E3834",
      "bitDepth": 16,
      "colorSpace": "sRGB",
      "contentLength": 105501473,
      "maxIntensity": 68,
      "mimeType": "image/x-exr",
      "minIntensity": 32,
      "name": "Basecolor",
      "physicalSize": "0.5x1",
      "resolution": "4096x8192",
      "type": "basecolor",
      "uri": "skkvdgfc_8K_Basecolor.exr"
    },
    {
      "averageColor": "#3E3834",
      "bitDepth": 8,
      "colorSpace": "sRGB",
      "contentLength": 13625309,
      "maxIntensity": 68,
      "mimeType": "image/jpeg",
      "minIntensity": 32,
      "name": "Basecolor",
      "physicalSize": "0.5x1",
      "resolution": "4096x8192",
      "type": "basecolor",
      "uri": "skkvdgfc_8K_Basecolor.jpg"
    },
    {
      "averageColor": "#444444",
      "bitDepth": 32,
      "colorSpace": "Linear",
      "contentLength": 60250525,
      "maxIntensity": 255,
      "mimeType": "image/x-exr",
      "minIntensity": 0,
      "name": "Opacity",
      "physicalSize": "0.5x1",
      "resolution": "4096x8192",
      "type": "opacity",
      "uri": "skkvdgfc_8K_Opacity.exr"
    },
    {
      "averageColor": "#444444",
      "bitDepth": 8,
      "colorSpace": "Linear",
      "contentLength": 19204376,
      "maxIntensity": 255,
      "mimeType": "image/jpeg",
      "minIntensity": 0,
      "name": "Opacity",
      "physicalSize": "0.5x1",
      "resolution": "4096x8192",
      "type": "opacity",
      "uri": "skkvdgfc_8K_Opacity.jpg"
    },
    {
      "averageColor": "#383838",
      "bitDepth": 16,
      "colorSpace": "sRGB",
      "contentLength": 69902160,
      "maxIntensity": 58,
      "mimeType": "image/x-exr",
      "minIntensity": 51,
      "name": "Specular",
      "physicalSize": "0.5x1",
      "resolution": "4096x8192",
      "type": "specular",
      "uri": "skkvdgfc_8K_Specular.exr"
    },
    {
      "averageColor": "#383838",
      "bitDepth": 8,
      "colorSpace": "sRGB",
      "contentLength": 4387191,
      "maxIntensity": 58,
      "mimeType": "image/jpeg",
      "minIntensity": 51,
      "name": "Specular",
      "physicalSize": "0.5x1",
      "resolution": "4096x8192",
      "type": "specular",
      "uri": "skkvdgfc_8K_Specular.jpg"
    }
  ],
  "meta": [
    {
      "key": "scanArea",
      "name": "Scan Area",
      "value": "0.5x1 m"
    },
    {
      "key": "height",
      "name": "Height",
      "value": "20 m"
    },
    {
      "key": "tileable",
      "name": "Tileable",
      "value": false
    },
    {
      "key": "texelDensity",
      "name": "Texel Density",
      "value": "8192 px/m"
    },
    {
      "key": "calibration",
      "name": "Calibration",
      "value": "GretagMacbeth ColorChecker Color Rendition Chart"
    },
    {
      "key": "scanner",
      "name": "Scanner",
      "value": "MKX"
    }
  ],
  "models": [],
  "name": "Leakage",
  "pack": {
    "_id": "leakage",
    "name": "Leakage"
  },
  "physicalSize": null,
  "points": 1,
  "previews": {
    "images": [
      {
        "contentLength": 173945,
        "resolution": "360x360",
        "tags": [
          "thumb"
        ],
        "uri": "skkvdgfc_Grid_360.png"
      },
      {
        "contentLength": 234637,
        "resolution": "420x420",
        "tags": [
          "thumb"
        ],
        "uri": "skkvdgfc_Grid_420.png"
      },
      {
        "contentLength": 679566,
        "resolution": "720x720",
        "tags": [
          "thumb",
          "retina"
        ],
        "uri": "skkvdgfc_Grid_720.png"
      },
      {
        "contentLength": 916553,
        "resolution": "840x840",
        "tags": [
          "thumb",
          "retina"
        ],
        "uri": "skkvdgfc_Grid_840.png"
      },
      {
        "contentLength": 1676945,
        "resolution": "1440x768",
        "tags": [
          "preview",
          "clay"
        ],
        "uri": "skkvdgfc_PopupClay_1440.png"
      },
      {
        "contentLength": 3064852,
        "resolution": "1920x1080",
        "tags": [
          "preview",
          "clay"
        ],
        "uri": "skkvdgfc_PopupClay_1920.png"
      },
      {
        "contentLength": 6416464,
        "resolution": "2880x1536",
        "tags": [
          "preview",
          "clay",
          "retina"
        ],
        "uri": "skkvdgfc_PopupClay_2880.png"
      },
      {
        "contentLength": 11106336,
        "resolution": "3840x2160",
        "tags": [
          "preview",
          "clay",
          "retina"
        ],
        "uri": "skkvdgfc_PopupClay_3840.png"
      },
      {
        "contentLength": 1678636,
        "resolution": "1440x768",
        "tags": [
          "preview"
        ],
        "uri": "skkvdgfc_Popup_1440.png"
      },
      {
        "contentLength": 3110189,
        "resolution": "1920x1080",
        "tags": [
          "preview"
        ],
        "uri": "skkvdgfc_Popup_1920.png"
      },
      {
        "contentLength": 6481940,
        "resolution": "2880x1536",
        "tags": [
          "preview",
          "retina"
        ],
        "uri": "skkvdgfc_Popup_2880.png"
      },
      {
        "contentLength": 12057655,
        "resolution": "3840x2160",
        "tags": [
          "preview",
          "retina"
        ],
        "uri": "skkvdgfc_Popup_3840.png"
      }
    ],
    "relativeSize": "1x1",
    "scaleReferences": []
  },
  "process_date": "2024-04-17 17:41:51",
  "properties": [],
  "referencePreviews": {
    "maps": [],
    "models": []
  },
  "references": [],
  "revised": false,
  "semanticTags": {
    "architectural_style": {},
    "asset_type": "decal",
    "color": [
      "gray",
      "umber",
      "brown"
    ],
    "contains": [
      "grime",
      "seepage"
    ],
    "environment": [
      "urban",
      "industrial"
    ],
    "industry": [
      "games",
      "VFX"
    ],
    "interior_exterior": [
      "exterior",
      "interior"
    ],
    "latin_name": [],
    "locations": {},
    "maxSize": 1,
    "minSize": 0.5,
    "name": "Leakage",
    "orientation": [
      "wall"
    ],
    "resolution": 8192,
    "season": [],
    "state": [
      "old",
      "damaged"
    ],
    "subject_matter": "manmade",
    "theme": [
      "grunge",
      " flow"
    ]
  },
  "tags": [
    "decal",
    "dark",
    "gray",
    "grey",
    "brown",
    "umber",
    "leak",
    "flow",
    "seepage",
    "grunge",
    "grime",
    "archviz",
    "urban",
    "environments"
  ],
  "texelDensity": 8192,
  "texture_type": "basic",
  "ue_plugin_archives": [
    {
      "contentLength": 64018053,
      "gltfVersion": "2.0",
      "tier": 0,
      "type": "gltf",
      "uri": "ue_plugin_archives/tier_0/skkvdgfc_tier_0.zip",
      "version": 1
    },
    {
      "contentLength": 18645726,
      "gltfVersion": "2.0",
      "tier": 1,
      "type": "gltf",
      "uri": "ue_plugin_archives/tier_1/skkvdgfc_tier_1.zip",
      "version": 1
    },
    {
      "contentLength": 5131482,
      "gltfVersion": "2.0",
      "tier": 2,
      "type": "gltf",
      "uri": "ue_plugin_archives/tier_2/skkvdgfc_tier_2.zip",
      "version": 1
    },
    {
      "contentLength": 1280041,
      "gltfVersion": "2.0",
      "tier": 3,
      "type": "gltf",
      "uri": "ue_plugin_archives/tier_3/skkvdgfc_tier_3.zip",
      "version": 1
    }
  ],
  "version": 2
}